[
    {
        "name": "黃蝦花",
        "date": "2026-04-07",
        "notes": "春雨新綠洗遍\n金苞兔影初現\n簷外燕剪雨\n流連忘卻睏倦\n且住 且住\n花比兔兒更戀",
        "style": "原圖",
        "image_paths": [
            "植物拍照\\uploads\\20260718_131658.jpg"
        ]
    },
    {
        "name": "躑躅花(杜鵑花)",
        "date": "2026-02-18",
        "notes": "花躑躅  躅足忘歸\n人迷路  路轉啡香",
        "style": "原圖",
        "image_paths": [
            "植物拍照\\uploads\\20260718_134646_026324.jpg",
            "植物拍照\\uploads\\20260718_134646_027721.jpg",
            "植物拍照\\uploads\\20260718_134646_029021.jpg"
        ]
    },
    {
        "name": "薰衣草與秋海棠",
        "date": "2026-02-15",
        "notes": "薰衣草 草惹蝶依\n秋海棠 棠醉雲棲",
        "style": "原圖",
        "image_paths": [
            "植物拍照\\uploads\\20260718_144945_994219.jpg",
            "植物拍照\\uploads\\20260718_144945_995566.jpg"
        ]
    },
    {
        "name": "落羽松與梅花",
        "date": "2026-01-14",
        "notes": "落羽松 松守四時\n清枝梅 梅若初印",
        "style": "原圖",
        "image_paths": [
            "F:\\aider測試\\植物拍照\\data_images\\落羽松與梅花_1.jpg",
            "F:\\aider測試\\植物拍照\\data_images\\落羽松與梅花_2.jpg",
            "F:\\aider測試\\植物拍照\\data_images\\落羽松與梅花_3.jpg",
            "F:\\aider測試\\植物拍照\\data_images\\落羽松與梅花_4.jpg"
        ]
    },
    {
        "name": "光與影",
        "date": "2026-01-27",
        "notes": "影書難留 光談易逝(軼事)\n牆頭影 影跡為詩\n隙中光 光韻譜曲",
        "style": "原圖",
        "image_paths": [
            "F:\\aider測試\\植物拍照\\data_images\\光與影_1.jpg",
            "F:\\aider測試\\植物拍照\\data_images\\光與影_2.jpg",
            "F:\\aider測試\\植物拍照\\data_images\\光與影_3.jpg"
        ]
    }
]